wordgame/__init__.py
wordgame/__main__.py
wordgame/words.txt
wordgame/test/__init__.py
wordgame/test/test_countdown.py
wordgame/test/test_parse_arguments.py
wordgame/test/test_sort_words.py
wordgame/test/test_take.py
wordgame/test/test_words_list.py
wordgame-0.4.0.dist-info/METADATA
wordgame-0.4.0.dist-info/RECORD
wordgame-0.4.0.dist-info/WHEEL
wordgame-0.4.0.dist-info/top_level.txt
