Metadata-Version: 2.1
Name: wordgame
Version: 0.4.0
Summary: A solver for wordgames such as scrabble and countdown.
Home-page: https://github.com/AaronRobson/wordgame/
Author: Aaron Robson
Author-email: arobsonse@hotmail.co.uk
License: LICENSE.txt
Platform: UNKNOWN
Requires-Python: >=3.6
